logstash_sync/__init__.py
logstash_sync/camel_to_snake.py
logstash_sync/formatter.py
logstash_sync/handler_amqp.py
logstash_sync/handler_http.py
logstash_sync/handler_tcp.py
logstash_sync/handler_udp.py
logstash_sync-0.5.5.dist-info/LICENSE
logstash_sync-0.5.5.dist-info/METADATA
logstash_sync-0.5.5.dist-info/WHEEL
logstash_sync-0.5.5.dist-info/top_level.txt
logstash_sync-0.5.5.dist-info/RECORD
