Metadata-Version: 2.1
Name: logstash-sync
Version: 0.5.5
Summary: Python logging handler for Logstash.
Home-page: https://gitlab.com/Myrik/python3-logstash
Author: Sergey Yorsh
Author-email: myrik260138@tut.by
License: UNKNOWN
Platform: UNKNOWN
Classifier: Development Status :: 4 - Beta
Classifier: Intended Audience :: Developers
Classifier: License :: OSI Approved :: MIT License
Classifier: Operating System :: OS Independent
Classifier: Programming Language :: Python
Classifier: Programming Language :: Python :: 3
Classifier: Topic :: Software Development :: Libraries :: Python Modules
Classifier: Topic :: System :: Logging
License-File: LICENSE
